CMakeLists.txt
LICENSE.txt
MANIFEST.in
README.md
README.txt
casadi-config-version.cmake.in
casadi-config.cmake.in
requirements.txt
setup.py
casadi/.clang-tidy
casadi/.clang-tidy-wip
casadi/CMakeLists.txt
casadi/casadi.hpp
casadi/casadi_c.h
casadi/config.h.cmake
casadi/generate_runtime.cmake
casadi/mem.h
casadi/core/CMakeLists.txt
casadi/core/assertion.cpp
casadi/core/assertion.hpp
casadi/core/bilin.cpp
casadi/core/bilin.hpp
casadi/core/binary_mx.hpp
casadi/core/binary_mx_impl.hpp
casadi/core/binary_sx.hpp
casadi/core/bspline.cpp
casadi/core/bspline.hpp
casadi/core/bspline_impl.hpp
casadi/core/calculus.hpp
casadi/core/callback.cpp
casadi/core/callback.hpp
casadi/core/callback_internal.cpp
casadi/core/callback_internal.hpp
casadi/core/casadi.def
casadi/core/casadi_c.cpp
casadi/core/casadi_call.cpp
casadi/core/casadi_call.hpp
casadi/core/casadi_cli.cpp
casadi/core/casadi_common.cpp
casadi/core/casadi_common.hpp
casadi/core/casadi_enum.hpp
casadi/core/casadi_find.cpp
casadi/core/casadi_find.hpp
casadi/core/casadi_interrupt.cpp
casadi/core/casadi_interrupt.hpp
casadi/core/casadi_limits.hpp
casadi/core/casadi_logger.cpp
casadi/core/casadi_logger.hpp
casadi/core/casadi_low.cpp
casadi/core/casadi_low.hpp
casadi/core/casadi_meta.cpp
casadi/core/casadi_meta.hpp
casadi/core/casadi_misc.cpp
casadi/core/casadi_misc.hpp
casadi/core/casadi_os.cpp
casadi/core/casadi_os.hpp
casadi/core/casadi_types.hpp
casadi/core/code_generator.cpp
casadi/core/code_generator.hpp
casadi/core/concat.cpp
casadi/core/concat.hpp
casadi/core/conic.cpp
casadi/core/conic.hpp
casadi/core/conic_impl.hpp
casadi/core/constant_mx.cpp
casadi/core/constant_mx.hpp
casadi/core/constant_sx.hpp
casadi/core/convexify.cpp
casadi/core/convexify.hpp
casadi/core/core.hpp
casadi/core/dae_builder.cpp
casadi/core/dae_builder.hpp
casadi/core/dae_builder_internal.cpp
casadi/core/dae_builder_internal.hpp
casadi/core/determinant.cpp
casadi/core/determinant.hpp
casadi/core/dm.hpp
casadi/core/dm_fwd.hpp
casadi_fork.egg-info/PKG-INFO
casadi_fork.egg-info/SOURCES.txt
casadi_fork.egg-info/dependency_links.txt
casadi_fork.egg-info/not-zip-safe
casadi_fork.egg-info/requires.txt
casadi_fork.egg-info/top_level.txt
