Metadata-Version: 2.1
Name: casadi-fork
Version: 3.6.5
Summary:  CasADi -- framework for algorithmic differentiation and numeric optimization
Home-page: http://casadi.org
Author: Joel Andersson, Joris Gillis, Greg Horn
Author-email: developer_first_name@casadi.org
Maintainer: Joris Gillis
Maintainer-email: joris@casadi.org
License: UNKNOWN
Download-URL: http://install.casadi.org
Project-URL: Bug Tracker, https://github.com/casadi/casadi/issues
Project-URL: Documentation, http://docs.casadi.org
Project-URL: Source Code, https://github.com/casadi/casadi
Platform: UNKNOWN
Classifier: Development Status :: 5 - Production/Stable
Classifier: Natural Language :: English
Classifier: Intended Audience :: Science/Research
Classifier: Operating System :: OS Independent
Classifier: Programming Language :: C++
Classifier: Programming Language :: Python
Classifier: Programming Language :: Python :: 2
Classifier: Programming Language :: Python :: 2.7
Classifier: Programming Language :: Python :: 3
Classifier: Programming Language :: Python :: 3.5
Classifier: Programming Language :: Python :: 3.6
Classifier: Programming Language :: Python :: 3.7
Classifier: Programming Language :: Python :: 3.8
Classifier: Programming Language :: Python :: 3.9
Classifier: Programming Language :: Python :: 3.10
Classifier: Programming Language :: Python :: 3.11
Classifier: Programming Language :: Python :: 3.12
Classifier: License :: OSI Approved :: GNU Lesser General Public License v3 or later (LGPLv3+)
